fds/__init__.py
fds/sdk/__init__.py
fds/sdk/BarraPortfolioOptimizer/__init__.py
fds/sdk/BarraPortfolioOptimizer/api_client.py
fds/sdk/BarraPortfolioOptimizer/configuration.py
fds/sdk/BarraPortfolioOptimizer/exceptions.py
fds/sdk/BarraPortfolioOptimizer/model_utils.py
fds/sdk/BarraPortfolioOptimizer/rest.py
fds/sdk/BarraPortfolioOptimizer/api/__init__.py
fds/sdk/BarraPortfolioOptimizer/api/accounts_api.py
fds/sdk/BarraPortfolioOptimizer/api/bpm_optimizer_api.py
fds/sdk/BarraPortfolioOptimizer/api/currencies_api.py
fds/sdk/BarraPortfolioOptimizer/api/strategy_documents_api.py
fds/sdk/BarraPortfolioOptimizer/apis/__init__.py
fds/sdk/BarraPortfolioOptimizer/model/__init__.py
fds/sdk/BarraPortfolioOptimizer/model/account_directories.py
fds/sdk/BarraPortfolioOptimizer/model/account_directories_root.py
fds/sdk/BarraPortfolioOptimizer/model/bpm_optimization.py
fds/sdk/BarraPortfolioOptimizer/model/bpm_optimization_parameters.py
fds/sdk/BarraPortfolioOptimizer/model/bpm_optimization_parameters_root.py
fds/sdk/BarraPortfolioOptimizer/model/bpm_optimizer_strategy.py
fds/sdk/BarraPortfolioOptimizer/model/bpm_optimizer_strategy_alpha_override.py
fds/sdk/BarraPortfolioOptimizer/model/bpm_optimizer_strategy_overrides.py
fds/sdk/BarraPortfolioOptimizer/model/calculation_info.py
fds/sdk/BarraPortfolioOptimizer/model/calculation_info_root.py
fds/sdk/BarraPortfolioOptimizer/model/client_error_response.py
fds/sdk/BarraPortfolioOptimizer/model/constraint_action.py
fds/sdk/BarraPortfolioOptimizer/model/currency.py
fds/sdk/BarraPortfolioOptimizer/model/currency_root.py
fds/sdk/BarraPortfolioOptimizer/model/document_directories.py
fds/sdk/BarraPortfolioOptimizer/model/document_directories_root.py
fds/sdk/BarraPortfolioOptimizer/model/error.py
fds/sdk/BarraPortfolioOptimizer/model/error_source.py
fds/sdk/BarraPortfolioOptimizer/model/object_root.py
fds/sdk/BarraPortfolioOptimizer/model/optimal_portfolio.py
fds/sdk/BarraPortfolioOptimizer/model/optimizer_account.py
fds.sdk.BarraPortfolioOptimizer-0.21.14.dist-info/LICENSE
fds.sdk.BarraPortfolioOptimizer-0.21.14.dist-info/METADATA
fds.sdk.BarraPortfolioOptimizer-0.21.14.dist-info/WHEEL
fds.sdk.BarraPortfolioOptimizer-0.21.14.dist-info/top_level.txt
fds.sdk.BarraPortfolioOptimizer-0.21.14.dist-info/RECORD
